{
    "ansi-0-hex": "#eeeeee",
    "ansi-1-hex": "#bcbcbc",
    "ansi-10-hex": "#8700af",
    "ansi-11-hex": "#d70087",
    "ansi-12-hex": "#d75f00",
    "ansi-13-hex": "#005faf",
    "ansi-14-hex": "#d75f00",
    "ansi-15-hex": "#878787",
    "ansi-2-hex": "#8700af",
    "ansi-3-hex": "#d70087",
    "ansi-4-hex": "#d75f00",
    "ansi-5-hex": "#005faf",
    "ansi-6-hex": "#d75f00",
    "ansi-7-hex": "#444444",
    "ansi-8-hex": "#5f8700",
    "ansi-9-hex": "#bcbcbc",
    "background-hex": "#eeeeee",
    "cursor-hex": "#444444",
    "foreground-hex": "#444444",
    "selection-hex": "#005f87",
    "selection-text-hex": "#af0000",
    "theme-author": "Jon Leopard (http://github.com/jonleopard), based on PaperColor Theme (https://github.com/NLKNguyen/papercolor-theme)",
    "theme-name": "PaperColor Light",
    "theme-slug": "papercolor-light",
    "theme-source": "base16",
    "theme-source-slug": "base16",
    "theme-variant": "light"
}
