{
    "ansi-0-hex": "#000000",
    "ansi-1-hex": "#ff0000",
    "ansi-10-hex": "#00ff00",
    "ansi-11-hex": "#ffff00",
    "ansi-12-hex": "#0000ff",
    "ansi-13-hex": "#ff00ff",
    "ansi-14-hex": "#00ffff",
    "ansi-15-hex": "#ffffff",
    "ansi-2-hex": "#00ff00",
    "ansi-3-hex": "#ffff00",
    "ansi-4-hex": "#0000ff",
    "ansi-5-hex": "#ff00ff",
    "ansi-6-hex": "#00ffff",
    "ansi-7-hex": "#c0c0c0",
    "ansi-8-hex": "#808080",
    "ansi-9-hex": "#ff0000",
    "background-hex": "#000000",
    "cursor-hex": "#c0c0c0",
    "foreground-hex": "#c0c0c0",
    "selection-hex": "#e0e0e0",
    "selection-text-hex": "#2a2a2a",
    "theme-author": "Fergus Collins (https://github.com/ferguscollins)",
    "theme-name": "Windows NT",
    "theme-slug": "windows-nt",
    "theme-source": "base16",
    "theme-source-slug": "base16",
    "theme-variant": "dark"
}
