{
    "ansi-0-hex": "#000000",
    "ansi-1-hex": "#ff1b00",
    "ansi-10-hex": "#a5df55",
    "ansi-11-hex": "#fbe749",
    "ansi-12-hex": "#89bdff",
    "ansi-13-hex": "#bf00c0",
    "ansi-14-hex": "#85e9fe",
    "ansi-15-hex": "#dbdbdb",
    "ansi-2-hex": "#a5df55",
    "ansi-3-hex": "#89bdff",
    "ansi-4-hex": "#486387",
    "ansi-5-hex": "#fc5ef0",
    "ansi-6-hex": "#85e9fe",
    "ansi-7-hex": "#a1a1a1",
    "ansi-8-hex": "#4e4e4e",
    "ansi-9-hex": "#d41c00",
    "background-hex": "#000000",
    "cursor-hex": "#a1a1a1",
    "foreground-hex": "#a1a1a1",
    "selection-hex": "#cbcbcb",
    "selection-text-hex": "#343434",
    "theme-author": "FredHappyface (https://github.com/fredHappyface)",
    "theme-name": "Hurtado",
    "theme-slug": "hurtado",
    "theme-source": "base24",
    "theme-source-slug": "base24",
    "theme-variant": "dark"
}
