{
    "ansi-0-hex": "#000000",
    "ansi-1-hex": "#DA4939",
    "ansi-10-hex": "#83D182",
    "ansi-11-hex": "#FFFF7C",
    "ansi-12-hex": "#9FCEF0",
    "ansi-13-hex": "#FFFFFF",
    "ansi-14-hex": "#A0CEF0",
    "ansi-15-hex": "#FFFFFF",
    "ansi-2-hex": "#519F50",
    "ansi-3-hex": "#FFD24A",
    "ansi-4-hex": "#6D9CBE",
    "ansi-5-hex": "#D0D0FF",
    "ansi-6-hex": "#6E9CBE",
    "ansi-7-hex": "#FFFFFF",
    "ansi-8-hex": "#323232",
    "ansi-9-hex": "#FF7B6B",
    "background-hex": "#2B2B2B",
    "cursor-hex": "#E6E1DC",
    "foreground-hex": "#E6E1DC",
    "selection-hex": "#FFFFFF",
    "selection-text-hex": "#000000",
    "theme-author": "",
    "theme-name": "Broadcast",
    "theme-slug": "broadcast",
    "theme-source": "gogh",
    "theme-source-slug": "gogh",
    "theme-variant": ""
}
