{
    "ansi-0": {
        "hex": "#1a1a1a",
        "hexterm": "1a/1a/1a"
    },
    "ansi-1": {
        "hex": "#ff929f",
        "hexterm": "ff/92/9f"
    },
    "ansi-10": {
        "hex": "#88c400",
        "hexterm": "88/c4/00"
    },
    "ansi-11": {
        "hex": "#d7ae00",
        "hexterm": "d7/ae/00"
    },
    "ansi-12": {
        "hex": "#8cb4f0",
        "hexterm": "8c/b4/f0"
    },
    "ansi-13": {
        "hex": "#de99f0",
        "hexterm": "de/99/f0"
    },
    "ansi-14": {
        "hex": "#00ca9a",
        "hexterm": "00/ca/9a"
    },
    "ansi-15": {
        "hex": "#e0e0e0",
        "hexterm": "e0/e0/e0"
    },
    "ansi-2": {
        "hex": "#5fc940",
        "hexterm": "5f/c9/40"
    },
    "ansi-3": {
        "hex": "#c5b300",
        "hexterm": "c5/b3/00"
    },
    "ansi-4": {
        "hex": "#5fb8ff",
        "hexterm": "5f/b8/ff"
    },
    "ansi-5": {
        "hex": "#ef91df",
        "hexterm": "ef/91/df"
    },
    "ansi-6": {
        "hex": "#1dc5c3",
        "hexterm": "1d/c5/c3"
    },
    "ansi-7": {
        "hex": "#c4bdaf",
        "hexterm": "c4/bd/af"
    },
    "ansi-8": {
        "hex": "#242536",
        "hexterm": "24/25/36"
    },
    "ansi-9": {
        "hex": "#f69d6a",
        "hexterm": "f6/9d/6a"
    },
    "background": {
        "hex": "#1a1a1a",
        "hexterm": "1a/1a/1a"
    },
    "cursor": {
        "hex": "#e0e0e0",
        "hexterm": "e0/e0/e0"
    },
    "foreground": {
        "hex": "#e0e0e0",
        "hexterm": "e0/e0/e0"
    },
    "selection": {
        "hex": "#e0e0e0",
        "hexterm": "e0/e0/e0"
    },
    "selection-text": {
        "hex": "#1a1a1a",
        "hexterm": "1a/1a/1a"
    },
    "theme-author": "Protesilaos Stavrou (https://protesilaos.com)",
    "theme-name": "Tempus Night",
    "theme-slug": "tempus-night",
    "theme-source": "gogh",
    "theme-source-slug": "gogh",
    "theme-variant": "dark"
}
