{
    "ansi-0-hex": "#36283d",
    "ansi-1-hex": "#71ade9",
    "ansi-10-hex": "#e59db1",
    "ansi-11-hex": "#9ea0d3",
    "ansi-12-hex": "#8bb8e9",
    "ansi-13-hex": "#e1b4ce",
    "ansi-14-hex": "#cedaeb",
    "ansi-15-hex": "#fffefe",
    "ansi-2-hex": "#ab8cae",
    "ansi-3-hex": "#9ea0d3",
    "ansi-4-hex": "#8bb8e9",
    "ansi-5-hex": "#e1b4ce",
    "ansi-6-hex": "#cedaeb",
    "ansi-7-hex": "#9098a4",
    "ansi-8-hex": "#71ade9",
    "ansi-9-hex": "#ab8cae",
    "background-hex": "#36283d",
    "cursor-hex": "#cedaeb",
    "foreground-hex": "#cedaeb",
    "selection-hex": "#cedaeb",
    "selection-text-hex": "#36283d",
    "theme-author": "Ruhannn (https://github.com/ruhannn)",
    "theme-name": "Ayaka",
    "theme-slug": "ayaka",
    "theme-source": "gogh",
    "theme-source-slug": "gogh",
    "theme-variant": "dark"
}
