{
    "ansi-0-hex": "#2D283F",
    "ansi-1-hex": "#ED2261",
    "ansi-10-hex": "#53AA5E",
    "ansi-11-hex": "#B2DC87",
    "ansi-12-hex": "#A9BCEC",
    "ansi-13-hex": "#AD81C2",
    "ansi-14-hex": "#9DE3EB",
    "ansi-15-hex": "#A288F7",
    "ansi-2-hex": "#1FA91B",
    "ansi-3-hex": "#8DDC20",
    "ansi-4-hex": "#487DF4",
    "ansi-5-hex": "#8D35C9",
    "ansi-6-hex": "#3BDEED",
    "ansi-7-hex": "#9E9EA0",
    "ansi-8-hex": "#59516A",
    "ansi-9-hex": "#F0729A",
    "background-hex": "#171423",
    "cursor-hex": "#9F9FA1",
    "foreground-hex": "#9F9FA1",
    "selection-hex": "#9E9EA0",
    "selection-text-hex": "#61615f",
    "theme-author": "",
    "theme-name": "Grape",
    "theme-slug": "grape",
    "theme-source": "gogh",
    "theme-source-slug": "gogh",
    "theme-variant": ""
}
