{
    "ansi-0-hex": "#878787",
    "ansi-1-hex": "#FF6600",
    "ansi-10-hex": "#00FF00",
    "ansi-11-hex": "#FFFF00",
    "ansi-12-hex": "#0000FF",
    "ansi-13-hex": "#FF00FF",
    "ansi-14-hex": "#00FFFF",
    "ansi-15-hex": "#E5E5E5",
    "ansi-2-hex": "#CCFF04",
    "ansi-3-hex": "#FFCC00",
    "ansi-4-hex": "#44B4CC",
    "ansi-5-hex": "#9933CC",
    "ansi-6-hex": "#44B4CC",
    "ansi-7-hex": "#F5F5F5",
    "ansi-8-hex": "#555555",
    "ansi-9-hex": "#FF0000",
    "background-hex": "#000000",
    "cursor-hex": "#FFFFFF",
    "foreground-hex": "#FFFFFF",
    "selection-hex": "#F5F5F5",
    "selection-text-hex": "#0a0a0a",
    "theme-author": "",
    "theme-name": "Vibrant Ink",
    "theme-slug": "vibrant-ink",
    "theme-source": "gogh",
    "theme-source-slug": "gogh",
    "theme-variant": ""
}
