{
    "ansi-0-hex": "#f2e5bc",
    "ansi-1-hex": "#c14a4a",
    "ansi-10-hex": "#6c782e",
    "ansi-11-hex": "#b47109",
    "ansi-12-hex": "#45707a",
    "ansi-13-hex": "#945e80",
    "ansi-14-hex": "#4c7a5d",
    "ansi-15-hex": "#654735",
    "ansi-2-hex": "#6c782e",
    "ansi-3-hex": "#b47109",
    "ansi-4-hex": "#45707a",
    "ansi-5-hex": "#945e80",
    "ansi-6-hex": "#4c7a5d",
    "ansi-7-hex": "#654735",
    "ansi-8-hex": "#f2e5bc",
    "ansi-9-hex": "#c14a4a",
    "background-hex": "#fbf1c7",
    "cursor-hex": "#654735",
    "foreground-hex": "#654735",
    "selection-hex": "#654735",
    "selection-text-hex": "#9ab8ca",
    "theme-author": "",
    "theme-name": "Gruvbox Material Light",
    "theme-slug": "gruvbox-material-light",
    "theme-source": "gogh",
    "theme-source-slug": "gogh",
    "theme-variant": ""
}
