{
    "ansi-0": {
        "hex": "#22221b",
        "hexterm": "22/22/1b"
    },
    "ansi-1": {
        "hex": "#ba6236",
        "hexterm": "ba/62/36"
    },
    "ansi-10": {
        "hex": "#7d9726",
        "hexterm": "7d/97/26"
    },
    "ansi-11": {
        "hex": "#a5980d",
        "hexterm": "a5/98/0d"
    },
    "ansi-12": {
        "hex": "#36a166",
        "hexterm": "36/a1/66"
    },
    "ansi-13": {
        "hex": "#5f9182",
        "hexterm": "5f/91/82"
    },
    "ansi-14": {
        "hex": "#5b9d48",
        "hexterm": "5b/9d/48"
    },
    "ansi-15": {
        "hex": "#f4f3ec",
        "hexterm": "f4/f3/ec"
    },
    "ansi-2": {
        "hex": "#7d9726",
        "hexterm": "7d/97/26"
    },
    "ansi-3": {
        "hex": "#a5980d",
        "hexterm": "a5/98/0d"
    },
    "ansi-4": {
        "hex": "#36a166",
        "hexterm": "36/a1/66"
    },
    "ansi-5": {
        "hex": "#5f9182",
        "hexterm": "5f/91/82"
    },
    "ansi-6": {
        "hex": "#5b9d48",
        "hexterm": "5b/9d/48"
    },
    "ansi-7": {
        "hex": "#929181",
        "hexterm": "92/91/81"
    },
    "ansi-8": {
        "hex": "#6c6b5a",
        "hexterm": "6c/6b/5a"
    },
    "ansi-9": {
        "hex": "#ae7313",
        "hexterm": "ae/73/13"
    },
    "background": {
        "hex": "#22221b",
        "hexterm": "22/22/1b"
    },
    "cursor": {
        "hex": "#878573",
        "hexterm": "87/85/73"
    },
    "foreground": {
        "hex": "#878573",
        "hexterm": "87/85/73"
    },
    "selection": {
        "hex": "#878573",
        "hexterm": "87/85/73"
    },
    "selection-text": {
        "hex": "#22221b",
        "hexterm": "22/22/1b"
    },
    "theme-author": "Bram de Haan (http://atelierbram.github.io/syntax-highlighting/atelier-schemes/estuary)",
    "theme-name": "Atelier Estuary",
    "theme-slug": "atelier-estuary",
    "theme-source": "gogh",
    "theme-source-slug": "gogh",
    "theme-variant": "dark"
}
