{
    "ansi-0": {
        "hex": "#101016",
        "hexterm": "10/10/16"
    },
    "ansi-1": {
        "hex": "#fe0050",
        "hexterm": "fe/00/50"
    },
    "ansi-10": {
        "hex": "#5ff967",
        "hexterm": "5f/f9/67"
    },
    "ansi-11": {
        "hex": "#fefb67",
        "hexterm": "fe/fb/67"
    },
    "ansi-12": {
        "hex": "#6871fe",
        "hexterm": "68/71/fe"
    },
    "ansi-13": {
        "hex": "#bc35eb",
        "hexterm": "bc/35/eb"
    },
    "ansi-14": {
        "hex": "#5ffdfe",
        "hexterm": "5f/fd/fe"
    },
    "ansi-15": {
        "hex": "#fefefe",
        "hexterm": "fe/fe/fe"
    },
    "ansi-2": {
        "hex": "#00db83",
        "hexterm": "00/db/83"
    },
    "ansi-3": {
        "hex": "#faf844",
        "hexterm": "fa/f8/44"
    },
    "ansi-4": {
        "hex": "#0170b6",
        "hexterm": "01/70/b6"
    },
    "ansi-5": {
        "hex": "#c930c7",
        "hexterm": "c9/30/c7"
    },
    "ansi-6": {
        "hex": "#00c5c7",
        "hexterm": "00/c5/c7"
    },
    "ansi-7": {
        "hex": "#c7c7c7",
        "hexterm": "c7/c7/c7"
    },
    "ansi-8": {
        "hex": "#676767",
        "hexterm": "67/67/67"
    },
    "ansi-9": {
        "hex": "#fe6d67",
        "hexterm": "fe/6d/67"
    },
    "background": {
        "hex": "#0f1116",
        "hexterm": "0f/11/16"
    },
    "cursor": {
        "hex": "#76fe9f",
        "hexterm": "76/fe/9f"
    },
    "foreground": {
        "hex": "#e31950",
        "hexterm": "e3/19/50"
    },
    "selection": {
        "hex": "#c1ddfe",
        "hexterm": "c1/dd/fe"
    },
    "selection-text": {
        "hex": "#000000",
        "hexterm": "00/00/00"
    },
    "theme-author": "unknown",
    "theme-name": "CyberpunkScarletProtocol",
    "theme-slug": "cyberpunkscarletprotocol",
    "theme-source": "iterm",
    "theme-source-slug": "iterm",
    "theme-variant": "dark"
}
