{
    "ansi-0": {
        "hex": "#000000",
        "hexterm": "00/00/00"
    },
    "ansi-1": {
        "hex": "#fb4245",
        "hexterm": "fb/42/45"
    },
    "ansi-10": {
        "hex": "#50fa7b",
        "hexterm": "50/fa/7b"
    },
    "ansi-11": {
        "hex": "#f0fa8b",
        "hexterm": "f0/fa/8b"
    },
    "ansi-12": {
        "hex": "#49b9fe",
        "hexterm": "49/b9/fe"
    },
    "ansi-13": {
        "hex": "#fb4cb3",
        "hexterm": "fb/4c/b3"
    },
    "ansi-14": {
        "hex": "#8be9fd",
        "hexterm": "8b/e9/fd"
    },
    "ansi-15": {
        "hex": "#ededec",
        "hexterm": "ed/ed/ec"
    },
    "ansi-2": {
        "hex": "#50fa7b",
        "hexterm": "50/fa/7b"
    },
    "ansi-3": {
        "hex": "#f0fa8b",
        "hexterm": "f0/fa/8b"
    },
    "ansi-4": {
        "hex": "#49b9fe",
        "hexterm": "49/b9/fe"
    },
    "ansi-5": {
        "hex": "#fb4cb3",
        "hexterm": "fb/4c/b3"
    },
    "ansi-6": {
        "hex": "#8be9fd",
        "hexterm": "8b/e9/fd"
    },
    "ansi-7": {
        "hex": "#ededec",
        "hexterm": "ed/ed/ec"
    },
    "ansi-8": {
        "hex": "#555555",
        "hexterm": "55/55/55"
    },
    "ansi-9": {
        "hex": "#fb4245",
        "hexterm": "fb/42/45"
    },
    "background": {
        "hex": "#1e1f28",
        "hexterm": "1e/1f/28"
    },
    "cursor": {
        "hex": "#e4e4e4",
        "hexterm": "e4/e4/e4"
    },
    "foreground": {
        "hex": "#ebece6",
        "hexterm": "eb/ec/e6"
    },
    "selection": {
        "hex": "#80adc5",
        "hexterm": "80/ad/c5"
    },
    "selection-text": {
        "hex": "#000000",
        "hexterm": "00/00/00"
    },
    "theme-author": "unknown",
    "theme-name": "Snazzy",
    "theme-slug": "snazzy",
    "theme-source": "iterm",
    "theme-source-slug": "iterm",
    "theme-variant": "dark"
}
