{
    "ansi-0-hex": "#000000",
    "ansi-1-hex": "#e4492b",
    "ansi-10-hex": "#61ee56",
    "ansi-11-hex": "#f2f055",
    "ansi-12-hex": "#0081ff",
    "ansi-13-hex": "#ff7dfe",
    "ansi-14-hex": "#60f6f8",
    "ansi-15-hex": "#f1f1f1",
    "ansi-2-hex": "#50d048",
    "ansi-3-hex": "#c5c340",
    "ansi-4-hex": "#3a75ff",
    "ansi-5-hex": "#ec65e7",
    "ansi-6-hex": "#4ed1dd",
    "ansi-7-hex": "#dcdcdc",
    "ansi-8-hex": "#9f9f9f",
    "ansi-9-hex": "#ff6640",
    "background-hex": "#feffff",
    "cursor-hex": "#4d4d4d",
    "foreground-hex": "#191919",
    "selection-hex": "#c1ddff",
    "selection-text-hex": "#191919",
    "theme-author": "unknown",
    "theme-name": "Pro Light",
    "theme-slug": "pro-light",
    "theme-source": "iterm",
    "theme-source-slug": "iterm",
    "theme-variant": "light"
}
