{
    "ansi-0-hex": "#242424",
    "ansi-1-hex": "#d61b15",
    "ansi-10-hex": "#6ac118",
    "ansi-11-hex": "#fdc70e",
    "ansi-12-hex": "#0855fe",
    "ansi-13-hex": "#fb004f",
    "ansi-14-hex": "#3ea7fc",
    "ansi-15-hex": "#8c00eb",
    "ansi-2-hex": "#59a413",
    "ansi-3-hex": "#fdb40b",
    "ansi-4-hex": "#053a8c",
    "ansi-5-hex": "#e40038",
    "ansi-6-hex": "#2594e0",
    "ansi-7-hex": "#eeeeee",
    "ansi-8-hex": "#4a4a4a",
    "ansi-9-hex": "#fb1b18",
    "background-hex": "#181818",
    "cursor-hex": "#bbbbbb",
    "foreground-hex": "#eeeeee",
    "selection-hex": "#b4d5ff",
    "selection-text-hex": "#000000",
    "theme-author": "unknown",
    "theme-name": "Elementary",
    "theme-slug": "elementary",
    "theme-source": "iterm",
    "theme-source-slug": "iterm",
    "theme-variant": "dark"
}
