{
    "ansi-0-hex": "#f0edec",
    "ansi-1-hex": "#a8334c",
    "ansi-10-hex": "#3f5a21",
    "ansi-11-hex": "#803c1b",
    "ansi-12-hex": "#1c5573",
    "ansi-13-hex": "#7b3b70",
    "ansi-14-hex": "#2b747c",
    "ansi-15-hex": "#4f5e68",
    "ansi-2-hex": "#4f6c31",
    "ansi-3-hex": "#944926",
    "ansi-4-hex": "#286386",
    "ansi-5-hex": "#88507c",
    "ansi-6-hex": "#3b8992",
    "ansi-7-hex": "#2b353b",
    "ansi-8-hex": "#cfc1ba",
    "ansi-9-hex": "#94253e",
    "background-hex": "#f0edec",
    "cursor-hex": "#2b353b",
    "foreground-hex": "#2b353b",
    "selection-hex": "#cbd9e3",
    "selection-text-hex": "#2b353b",
    "theme-author": "unknown",
    "theme-name": "zenbones_light",
    "theme-slug": "zenbones-light",
    "theme-source": "iterm",
    "theme-source-slug": "iterm",
    "theme-variant": "light"
}
