{
    "ansi-0": {
        "hex": "#21222c",
        "hexterm": "21/22/2c"
    },
    "ansi-1": {
        "hex": "#ff5555",
        "hexterm": "ff/55/55"
    },
    "ansi-10": {
        "hex": "#69ff94",
        "hexterm": "69/ff/94"
    },
    "ansi-11": {
        "hex": "#ffffa5",
        "hexterm": "ff/ff/a5"
    },
    "ansi-12": {
        "hex": "#d6acff",
        "hexterm": "d6/ac/ff"
    },
    "ansi-13": {
        "hex": "#ff92df",
        "hexterm": "ff/92/df"
    },
    "ansi-14": {
        "hex": "#a4ffff",
        "hexterm": "a4/ff/ff"
    },
    "ansi-15": {
        "hex": "#ffffff",
        "hexterm": "ff/ff/ff"
    },
    "ansi-2": {
        "hex": "#50fa7b",
        "hexterm": "50/fa/7b"
    },
    "ansi-3": {
        "hex": "#f1fa8c",
        "hexterm": "f1/fa/8c"
    },
    "ansi-4": {
        "hex": "#bd93f9",
        "hexterm": "bd/93/f9"
    },
    "ansi-5": {
        "hex": "#ff79c6",
        "hexterm": "ff/79/c6"
    },
    "ansi-6": {
        "hex": "#8be9fd",
        "hexterm": "8b/e9/fd"
    },
    "ansi-7": {
        "hex": "#f8f8f2",
        "hexterm": "f8/f8/f2"
    },
    "ansi-8": {
        "hex": "#6272a4",
        "hexterm": "62/72/a4"
    },
    "ansi-9": {
        "hex": "#ff6e6e",
        "hexterm": "ff/6e/6e"
    },
    "background": {
        "hex": "#282a36",
        "hexterm": "28/2a/36"
    },
    "cursor": {
        "hex": "#f8f8f2",
        "hexterm": "f8/f8/f2"
    },
    "foreground": {
        "hex": "#f8f8f2",
        "hexterm": "f8/f8/f2"
    },
    "selection": {
        "hex": "#44475a",
        "hexterm": "44/47/5a"
    },
    "selection-text": {
        "hex": "#ffffff",
        "hexterm": "ff/ff/ff"
    },
    "theme-author": "unknown",
    "theme-name": "Dracula",
    "theme-slug": "dracula",
    "theme-source": "iterm",
    "theme-source-slug": "iterm",
    "theme-variant": "dark"
}
