{
    "ansi-0": {
        "hex": "#373942",
        "hexterm": "37/39/42"
    },
    "ansi-1": {
        "hex": "#e45649",
        "hexterm": "e4/56/49"
    },
    "ansi-10": {
        "hex": "#98c379",
        "hexterm": "98/c3/79"
    },
    "ansi-11": {
        "hex": "#e4c07a",
        "hexterm": "e4/c0/7a"
    },
    "ansi-12": {
        "hex": "#61afef",
        "hexterm": "61/af/ef"
    },
    "ansi-13": {
        "hex": "#c577dd",
        "hexterm": "c5/77/dd"
    },
    "ansi-14": {
        "hex": "#56b5c1",
        "hexterm": "56/b5/c1"
    },
    "ansi-15": {
        "hex": "#ffffff",
        "hexterm": "ff/ff/ff"
    },
    "ansi-2": {
        "hex": "#4fa14f",
        "hexterm": "4f/a1/4f"
    },
    "ansi-3": {
        "hex": "#c08400",
        "hexterm": "c0/84/00"
    },
    "ansi-4": {
        "hex": "#0084bc",
        "hexterm": "00/84/bc"
    },
    "ansi-5": {
        "hex": "#a625a4",
        "hexterm": "a6/25/a4"
    },
    "ansi-6": {
        "hex": "#0996b3",
        "hexterm": "09/96/b3"
    },
    "ansi-7": {
        "hex": "#fafafa",
        "hexterm": "fa/fa/fa"
    },
    "ansi-8": {
        "hex": "#4f525d",
        "hexterm": "4f/52/5d"
    },
    "ansi-9": {
        "hex": "#df6c75",
        "hexterm": "df/6c/75"
    },
    "background": {
        "hex": "#fafafa",
        "hexterm": "fa/fa/fa"
    },
    "cursor": {
        "hex": "#beceff",
        "hexterm": "be/ce/ff"
    },
    "foreground": {
        "hex": "#373942",
        "hexterm": "37/39/42"
    },
    "selection": {
        "hex": "#beceff",
        "hexterm": "be/ce/ff"
    },
    "selection-text": {
        "hex": "#373942",
        "hexterm": "37/39/42"
    },
    "theme-author": "unknown",
    "theme-name": "OneHalfLight",
    "theme-slug": "onehalflight",
    "theme-source": "iterm",
    "theme-source-slug": "iterm",
    "theme-variant": "light"
}
